mxl/opentelemetry/__init__.py
mxl/opentelemetry/baggage.py
mxl/opentelemetry/distro.py
mxl/opentelemetry/logs.py
mxl/opentelemetry/manual.py
mxl/opentelemetry/metrics.py
mxl/opentelemetry/options.py
mxl/opentelemetry/resource.py
mxl/opentelemetry/sampler.py
mxl/opentelemetry/trace.py
mxl/opentelemetry/version.py
safaricom_mxl_python-0.1.1.dist-info/METADATA
safaricom_mxl_python-0.1.1.dist-info/WHEEL
safaricom_mxl_python-0.1.1.dist-info/entry_points.txt
safaricom_mxl_python-0.1.1.dist-info/RECORD
